minha_biblioteca_pitagoras/__init__.py
minha_biblioteca_pitagoras/teorema_pitagoras.py
minha_biblioteca_pitagoras-0.1.0.dist-info/METADATA
minha_biblioteca_pitagoras-0.1.0.dist-info/WHEEL
minha_biblioteca_pitagoras-0.1.0.dist-info/top_level.txt
minha_biblioteca_pitagoras-0.1.0.dist-info/RECORD
