Metadata-Version: 2.4
Name: minha-biblioteca-pitagoras
Version: 0.1.0
Summary: Uma biblioteca com função para calcular o Teorema de Pitágoras, criada no curso de Python da Nersant
Author-email: Marcelo Kamei <marcelokamei78@gmail.com>
License: MIT
Requires-Python: >=3.8
